pandas_finance/__init__.py
pandas_finance/api.py
pandas_finance/tests/__init__.py
pandas_finance/tests/test_api.py
pandas_finance-0.1.3.dist-info/LICENSE.md
pandas_finance-0.1.3.dist-info/METADATA
pandas_finance-0.1.3.dist-info/WHEEL
pandas_finance-0.1.3.dist-info/top_level.txt
pandas_finance-0.1.3.dist-info/RECORD
