Metadata-Version: 2.1
Name: pandas-finance
Version: 0.1.3
Summary: High level API for access to and analysis of financial data.
Home-page: https://github.com/davidastephens/pandas-finance
Author: David Stephens
Author-email: david@davidstephens.io
License: BSD License
Keywords: data
Classifier: Development Status :: 1 - Planning
Classifier: Environment :: Console
Classifier: Intended Audience :: Science/Research
Classifier: Operating System :: OS Independent
Classifier: Programming Language :: Cython
Classifier: Programming Language :: Python
Classifier: Programming Language :: Python :: 2
Classifier: Programming Language :: Python :: 2.7
Classifier: Programming Language :: Python :: 3
Classifier: Programming Language :: Python :: 3.2
Classifier: Programming Language :: Python :: 3.3
Classifier: Programming Language :: Python :: 3.4
Classifier: Programming Language :: Python :: 3.5
Classifier: Programming Language :: Python :: 3.6
Classifier: Topic :: Scientific/Engineering
License-File: LICENSE.md
Requires-Dist: pandas
Requires-Dist: requests-cache
Requires-Dist: pandas-datareader (>=0.7.0)
Requires-Dist: empyrical
